{
    "description": "replication of the naturalistic meta-analysis by Bottenhorn et al (2018)",
    "exclusion_criteria": [
        "static stimulus",
        "age <18"
    ],
    "inclusion_criteria": [],
    "search_to_pmids": {
        "\"naturalistic\" AND (\"fmri\" OR \"functional MRI\" OR \"functional neuroimaging\") ": [
            "9741778",
            "29754022",
            "26259016",
            "28375078",
            "26390850",
            "28630254",
            "19733672",
            "24949579",
            "29396524",
            "26679327",
            "28951452",
            "16167192",
            "22723774",
            "29993727",
            "26574501",
            "23103518",
            "23146252",
            "11788737",
            "27010577",
            "21709175",
            "26097689",
            "24872535",
            "22924089",
            "25842290",
            "25892594",
            "28777996",
            "25826284",
            "27126841",
            "22905026",
            "24553284",
            "24269803",
            "27445760",
            "15134843",
            "25654257",
            "26833917",
            "21094258",
            "24265613",
            "30217543",
            "28476662",
            "23607410",
            "19107751",
            "24685291",
            "23933473",
            "27358450",
            "29780313",
            "23447619",
            "30038566",
            "22245643",
            "22403536",
            "29409793",
            "27208858",
            "25702259",
            "25626060",
            "21861684",
            "19360650",
            "19945536",
            "28548462",
            "26112251",
            "26143014",
            "29272294",
            "22609273",
            "25662868",
            "26209860",
            "22206836",
            "28922834",
            "30154703",
            "21334443",
            "19233234",
            "22877840",
            "18414408",
            "16102242",
            "19539998",
            "20949046",
            "21945275",
            "27346546",
            "24550818",
            "27720819",
            "20132831",
            "28801255",
            "30032360",
            "22496909",
            "23683790",
            "27053211",
            "11906703",
            "28536514",
            "29588124",
            "27776563",
            "25267658",
            "29702443",
            "26791203",
            "23810975",
            "17618161",
            "27986636",
            "29335643",
            "28295803",
            "29642002",
            "22675289",
            "29779744",
            "29198274",
            "25695154",
            "22838740",
            "30285056",
            "29902585",
            "28420129",
            "29467495",
            "25084224",
            "29126097",
            "23296187",
            "24137106",
            "28625875",
            "19376237",
            "24132411",
            "27496338",
            "28029198",
            "29486325",
            "20428497",
            "29563861",
            "21989084",
            "20339365",
            "28369458",
            "27927958",
            "24581119",
            "15068912",
            "26241683",
            "28081125",
            "26290235",
            "20709442",
            "27704409",
            "28757306",
            "16156047",
            "30042652",
            "29396415",
            "26095530",
            "21718791",
            "20056152",
            "28349620",
            "29031531",
            "26364862",
            "23307636",
            "26579066",
            "26304192",
            "24294205",
            "20953234",
            "20598238",
            "30244003",
            "29488069",
            "24194828",
            "17553996",
            "28533739",
            "24333752",
            "29277645",
            "23116815",
            "23685719",
            "28648887",
            "21640981",
            "29867327",
            "27751943",
            "26892859",
            "21782031",
            "27704410",
            "26029133",
            "29535619",
            "20160850",
            "27550868",
            "26375211",
            "24044427",
            "26359527",
            "23202431",
            "28591837",
            "27903727",
            "29705065",
            "29795116",
            "21612817",
            "29596859",
            "23863519",
            "16628606",
            "25698698",
            "28737296",
            "28986207",
            "27629710",
            "22737112",
            "29896128",
            "27598534",
            "29257126",
            "23693090",
            "29729277",
            "26826515",
            "17412611",
            "28099241",
            "27129794",
            "29923098",
            "30212746",
            "29922144",
            "27195792",
            "29989271",
            "28129556",
            "30243125",
            "27660241",
            "27199708",
            "25862267",
            "22110619",
            "26860834",
            "26102225",
            "26226919",
            "23994457",
            "30290213",
            "28654963",
            "28879081",
            "29518569",
            "26638823",
            "18797499",
            "15038005",
            "23238964",
            "27386919",
            "30154691",
            "22116038",
            "23750290",
            "25829246",
            "25943766",
            "19239700",
            "29705690",
            "29679734",
            "28214981",
            "28842385",
            "28736170",
            "22248574",
            "25426054",
            "27065832",
            "30243926",
            "24564470",
            "27391013",
            "27375416",
            "23501053",
            "21782960",
            "24844746",
            "27932074",
            "26884746",
            "29997565",
            "28968727",
            "21925216",
            "27477592",
            "21915941",
            "22451493",
            "18633835",
            "28769835",
            "27564573",
            "27389788",
            "25246750",
            "25994970",
            "29962932",
            "25962953",
            "24706557",
            "22559794",
            "25798327",
            "26017384",
            "18698363",
            "27061771",
            "28456521",
            "26481673",
            "26132365",
            "25524650",
            "24972303",
            "29160744",
            "24583253",
            "24526569",
            "25773646",
            "29428580",
            "29249945",
            "25620526",
            "30301758",
            "28871034",
            "28094464",
            "28366871",
            "25312771",
            "25891796",
            "24550270",
            "28729161",
            "30249790",
            "15886020",
            "17549877",
            "25760689",
            "26888415"
        ]
    },
    "tags": [
        "Film viewing",
        "Music",
        "Music comprehension/production",
        "video games"
    ],
    "unmapped_pmids": []
}